ij/__init__.py
ij/cli.py
ij/core.py
ij/graph_ops.py
ij/transforms.py
ij/analyzers/__init__.py
ij/analyzers/python_analyzer.py
ij/converters/__init__.py
ij/converters/enhanced_text.py
ij/converters/llm_converter.py
ij/converters/text_to_ir.py
ij/parsers/__init__.py
ij/parsers/d2.py
ij/parsers/mermaid.py
ij/renderers/__init__.py
ij/renderers/d2.py
ij/renderers/graphviz.py
ij/renderers/mermaid.py
ij/renderers/plantuml.py
ij/renderers/sequence.py
ij-0.1.3.dist-info/METADATA
ij-0.1.3.dist-info/WHEEL
ij-0.1.3.dist-info/entry_points.txt
ij-0.1.3.dist-info/licenses/LICENSE
ij-0.1.3.dist-info/RECORD
