Metadata-Version: 2.4
Name: ij
Version: 0.1.3
Summary: Idea Junction - Connect of vague ideas and evolve them to fully functional systems
Project-URL: Homepage, https://github.com/i2mint/ij
Project-URL: Repository, https://github.com/i2mint/ij
License: mit
License-File: LICENSE
Requires-Python: >=3.10
Requires-Dist: graphviz>=0.20
Requires-Dist: networkx>=3.0
Provides-Extra: ai
Requires-Dist: openai>=1.0.0; extra == 'ai'
Provides-Extra: dev
Requires-Dist: pytest-cov>=4.0; extra == 'dev'
Requires-Dist: pytest>=7.0; extra == 'dev'
Requires-Dist: ruff>=0.1.0; extra == 'dev'
Provides-Extra: docs
Requires-Dist: sphinx-rtd-theme>=1.0; extra == 'docs'
Requires-Dist: sphinx>=6.0; extra == 'docs'
